GTS/__init__.py
GTS/gts.py
GTS/tools/__init__.py
GTS/tools/metrics.py
GTS/tools/visual.py
tools/__init__.py
tools/metrics.py
tools/visual.py
GGTS-0.0.2.dist-info/METADATA
GGTS-0.0.2.dist-info/WHEEL
GGTS-0.0.2.dist-info/top_level.txt
GGTS-0.0.2.dist-info/RECORD
